<configs>
	<append xpath="/recipes">
		<recipe name="q_EnemigosHF" count="1" craft_time="10">
			<ingredient name="bossTokenMineral" count="30"/>			
		</recipe>
		<recipe name="q_Jugger" count="1" craft_time="10">
			<ingredient name="bossTokenJugger" count="10"/>			
		</recipe>
		<recipe name="q_Pesadilla" count="1" craft_time="10">
			<ingredient name="bossTokenNight" count="10"/>			
		</recipe>
		<recipe name="q_Honor" count="1" craft_time="10">
			<ingredient name="bossTokenSoldier" count="10"/>			
		</recipe>
		<recipe name="q_Momia" count="1" craft_time="10">
			<ingredient name="bossTokenMummy" count="10"/>			
		</recipe>
		<recipe name="q_Gladiator" count="1" craft_time="5">
			<ingredient name="bossTokenGadiador" count="10"/>			
		</recipe>
		<recipe name="q_Cirujano" count="1" craft_time="5">
			<ingredient name="bossTokenCirujano" count="10"/>			
		</recipe>
		<recipe name="q_vodjanoj" count="1" craft_time="5">
			<ingredient name="bossTokenMortevoda" count="10"/>			
		</recipe>
		<recipe name="q_berial" count="1" craft_time="5">
			<ingredient name="bossTokenInfernal" count="10"/>			
		</recipe>
		<recipe name="q_jack" count="1" craft_time="5">
			<ingredient name="bossTokenHoarfrost" count="10"/>			
		</recipe>
		<recipe name="q_raijin" count="1" craft_time="5">
			<ingredient name="bossTokenShocker" count="10"/>			
		</recipe>
		<recipe name="q_patient0" count="1" craft_time="5">
			<ingredient name="bossTokenToxic" count="10"/>			
		</recipe>
		<recipe name="q_Gallinazilla" count="1" craft_time="5">
			<ingredient name="bossTokenNatu" count="10"/>			
		</recipe>
		
		<!-- <recipe name="q_VZ" count="1" craft_time="10">
			<ingredient name="bossTokenNatu" count="10"/>			
		</recipe> -->
	<!-- Added by HolyVentus 

		<recipe name="p_Hooligan_Force_1" count="1" craft_time="10">
			<ingredient name="bossTokenNight" count="20"/>
			<ingredient name="bossTokenMummy" count="20"/>
			<ingredient name="bossTokenCirujano" count="20"/>
		</recipe>
		<recipe name="p_Hooligan_Force_2" count="1" craft_time="10">
			<ingredient name="bossTokenJugger" count="20"/>
			<ingredient name="bossTokenSoldier" count="20"/>
			<ingredient name="bossTokenGadiador" count="20"/>	
		</recipe>
		<recipe name="q_Hooligan_Force_dummy" count="1" craft_time="10">
			<ingredient name="bossTokenMineral" count="30"/>
			<ingredient name="p_Hooligan_Force_1" count="1"/>
			<ingredient name="p_Hooligan_Force_2" count="1"/>
		</recipe>
	- END Added by HolyVentus -->		
		<recipe name="q_Hooligan_Force" count="1" craft_time="10">
			<ingredient name="bossTokenCirujano" count="20"/>
			<ingredient name="bossTokenNight" count="20"/>
			<ingredient name="bossTokenJugger" count="20"/>
			<ingredient name="bossTokenSoldier" count="20"/>
			<ingredient name="bossTokenMummy" count="20"/>	
			<ingredient name="bossTokenGadiador" count="20"/>	
		</recipe>		
		<recipe name="q_Taco" count="1" craft_time="5">
			<ingredient name="questFrag" count="100"/>			
		</recipe>		
		<recipe name="q_Gacha" count="1" craft_time="5">
			<ingredient name="questFrag" count="3"/>	
			<ingredient name="casinoCoin" count="1000"/>	
		</recipe>
		<!--ANCIENT-->
		
		<recipe name="ancientTool_UltimateHammer" count="1" craft_area="legenstation" craft_time="10" tags="learnable,workbenchCrafting,ancientCraft,LCLvl">
			<ingredient name="ResourceForgedPlatinum" count="4"/>
			<ingredient name="mythTool_DivineHammer" count="1"/>			
			<ingredient name="mythTool_DivineDriver" count="1"/>
			<ingredient name="unique_Newcomen" count="1"/>
			<ingredient name="bossTokenAncient" count="1"/>			
		</recipe>
				
		<recipe name="ancientRanged_Smg" count="1" craft_area="legenstation" craft_time="10" tags="learnable,workbenchCrafting,ancientCraft,LCLvl">
			<ingredient name="ResourceForgedPlatinum" count="2"/>
			<ingredient name="mithril" count="2"/>
			<ingredient name="mythRanged_Delta01" count="1"/>
			<ingredient name="unique_HyperBlaster" count="1"/>			
			<ingredient name="bossTokenAncient" count="1"/>
		</recipe>
		<recipe name="ancientRanged_Smg2" count="1" craft_area="legenstation" craft_time="10" tags="learnable,workbenchCrafting,ancientCraft,LCLvl">
			<ingredient name="ResourceForgedPlatinum" count="2"/>
			<ingredient name="mithril" count="2"/>
			<ingredient name="mythRanged_Delta01" count="1"/>
			<ingredient name="unique_HyperBlaster" count="1"/>			
			<ingredient name="bossTokenAncient" count="1"/>
		</recipe>				
		<recipe name="ancientRanged_Smg" count="1" craft_area="legenstation" craft_time="10" tags="learnable,workbenchCrafting,ancientCraft,LCLvl">		
			<ingredient name="ancientRanged_Smg2" count="1"/>
		</recipe>
		<recipe name="ancientRanged_Smg2" count="1" craft_area="legenstation" craft_time="10" tags="learnable,workbenchCrafting,ancientCraft,LCLvl">
			<ingredient name="ancientRanged_Smg" count="1"/>
		</recipe>

		<recipe name="ancientRanged_Desert" count="1" craft_area="legenstation" craft_time="10" tags="learnable,workbenchCrafting,ancientCraft,LCLvl">
			<ingredient name="ResourceForgedPlatinum" count="2"/>
			<ingredient name="mithril" count="2"/>
			<ingredient name="mythRanged_Peacemaker" count="1"/>
			<ingredient name="unique_Savery" count="1"/>			
			<ingredient name="bossTokenAncient" count="1"/>
		</recipe>
		<recipe name="ancientRanged_Desert2" count="1" craft_area="legenstation" craft_time="10" tags="learnable,workbenchCrafting,ancientCraft,LCLvl">
			<ingredient name="ResourceForgedPlatinum" count="2"/>
			<ingredient name="mithril" count="2"/>
			<ingredient name="mythRanged_Peacemaker" count="1"/>
			<ingredient name="unique_Savery" count="1"/>			
			<ingredient name="bossTokenAncient" count="1"/>
		</recipe>
		<recipe name="ancientRanged_Desert" count="1" craft_area="legenstation" craft_time="10" tags="learnable,workbenchCrafting,ancientCraft,LCLvl">
			<ingredient name="ancientRanged_Desert2" count="1"/>
		</recipe>
		<recipe name="ancientRanged_Desert2" count="1" craft_area="legenstation" craft_time="10" tags="learnable,workbenchCrafting,ancientCraft,LCLvl">	
			<ingredient name="ancientRanged_Desert" count="1"/>
		</recipe>

		<recipe name="ancientRanged_Shotgun" count="1" craft_area="legenstation" craft_time="10" tags="learnable,workbenchCrafting,ancientCraft,LCLvl">
			<ingredient name="ResourceForgedPlatinum" count="2"/>
			<ingredient name="mithril" count="2"/>
			<ingredient name="mythRanged_Destroyer" count="1"/>
			<ingredient name="unique_KronosXII" count="1"/>			
			<ingredient name="bossTokenAncient" count="1"/>
		</recipe>
		<recipe name="ancientRanged_Shotgun2" count="1" craft_area="legenstation" craft_time="10" tags="learnable,workbenchCrafting,ancientCraft,LCLvl">
			<ingredient name="ResourceForgedPlatinum" count="2"/>
			<ingredient name="mithril" count="2"/>
			<ingredient name="mythRanged_Destroyer" count="1"/>
			<ingredient name="unique_KronosXII" count="1"/>			
			<ingredient name="bossTokenAncient" count="1"/>
		</recipe>
		<recipe name="ancientRanged_Shotgun" count="1" craft_area="legenstation" craft_time="10" tags="learnable,workbenchCrafting,ancientCraft,LCLvl">		
			<ingredient name="ancientRanged_Shotgun2" count="1"/>
		</recipe>
		<recipe name="ancientRanged_Shotgun2" count="1" craft_area="legenstation" craft_time="10" tags="learnable,workbenchCrafting,ancientCraft,LCLvl">		
			<ingredient name="ancientRanged_Shotgun" count="1"/>
		</recipe>

		<recipe name="ancientRanged_Sniper" count="1" craft_area="legenstation" craft_time="10" tags="learnable,workbenchCrafting,ancientCraft,LCLvl">
			<ingredient name="ResourceForgedPlatinum" count="2"/>
			<ingredient name="mithril" count="2"/>
			<ingredient name="mythRanged_OneShot" count="1"/>
			<ingredient name="unique_Railgun" count="1"/>			
			<ingredient name="bossTokenAncient" count="1"/>
		</recipe>
		<recipe name="ancientRanged_Sniper2" count="1" craft_area="legenstation" craft_time="10" tags="learnable,workbenchCrafting,ancientCraft,LCLvl">
			<ingredient name="ResourceForgedPlatinum" count="2"/>
			<ingredient name="mithril" count="2"/>
			<ingredient name="mythRanged_OneShot" count="1"/>
			<ingredient name="unique_Railgun" count="1"/>			
			<ingredient name="bossTokenAncient" count="1"/>
		</recipe>
		<recipe name="ancientRanged_Sniper" count="1" craft_area="legenstation" craft_time="10" tags="learnable,workbenchCrafting,ancientCraft,LCLvl">
			<ingredient name="ancientRanged_Sniper2" count="1"/>
		</recipe>
		<recipe name="ancientRanged_Sniper2" count="1" craft_area="legenstation" craft_time="10" tags="learnable,workbenchCrafting,ancientCraft,LCLvl">
			<ingredient name="ancientRanged_Sniper" count="1"/>
		</recipe>

		<recipe name="ancientRanged_Auto" count="1" craft_area="legenstation" craft_time="10" tags="learnable,workbenchCrafting,ancientCraft,LCLvl">
			<ingredient name="ResourceForgedPlatinum" count="2"/>
			<ingredient name="mithril" count="2"/>
			<ingredient name="mythRanged_Dominator" count="1"/>
			<ingredient name="unique_Vulcan" count="1"/>			
			<ingredient name="bossTokenAncient" count="1"/>
		</recipe>
		<recipe name="ancientRanged_Auto2" count="1" craft_area="legenstation" craft_time="10" tags="learnable,workbenchCrafting,ancientCraft,LCLvl">
			<ingredient name="ResourceForgedPlatinum" count="2"/>
			<ingredient name="mithril" count="2"/>
			<ingredient name="mythRanged_Dominator" count="1"/>
			<ingredient name="unique_Vulcan" count="1"/>			
			<ingredient name="bossTokenAncient" count="1"/>
		</recipe>
		<recipe name="ancientRanged_Auto" count="1" craft_area="legenstation" craft_time="10" tags="learnable,workbenchCrafting,ancientCraft,LCLvl">
			<ingredient name="ancientRanged_Auto2" count="1"/>
		</recipe>
		<recipe name="ancientRanged_Auto2" count="1" craft_area="legenstation" craft_time="10" tags="learnable,workbenchCrafting,ancientCraft,LCLvl">
			<ingredient name="ancientRanged_Auto" count="1"/>
		</recipe>

		<recipe name="ancientMetalAlloy" count="5" craft_area="legenstation" craft_time="10" tags="learnable,workbenchCrafting,ancientCraft,LCLvl">			
			<ingredient name="bossTokenAncient" count="1"/>
			<ingredient name="mithril" count="3"/>
		 </recipe>
		<!--<recipe name="ancientArmorHelmet" count="1" craft_area="legenstation" craft_time="10" tags="learnable,workbenchCrafting,ancientCraft,LCLvl">			
			<ingredient name="ResourceForgedPlatinum" count="1"/>
			<ingredient name="LSAH" count="1"/>
			<ingredient name="LMAH" count="1"/>			
			<ingredient name="ancientMetalAlloy" count="1"/>
		</recipe>
		<recipe name="armorAncientArmor" count="1" craft_area="legenstation" craft_time="10" tags="learnable,workbenchCrafting,ancientCraft,LCLvl">			
			<ingredient name="ResourceForgedPlatinum" count="1"/>
			<ingredient name="LSAA" count="1"/>
			<ingredient name="LMAA" count="1"/>
			<ingredient name="ancientMetalAlloy" count="1"/>
		</recipe>
		<recipe name="armorAncientLegs" count="1" craft_area="legenstation" craft_time="10" tags="learnable,workbenchCrafting,ancientCraft,LCLvl">			
			<ingredient name="ResourceForgedPlatinum" count="1"/>			
			<ingredient name="LSAL" count="1"/>
			<ingredient name="LMAL" count="1"/>
			<ingredient name="ancientMetalAlloy" count="1"/>
		</recipe>
		<recipe name="armorAncientGloves" count="1" craft_area="legenstation" craft_time="10" tags="learnable,workbenchCrafting,ancientCraft,LCLvl">			
			<ingredient name="ResourceForgedPlatinum" count="1"/>
			<ingredient name="LSAG" count="1"/>
			<ingredient name="LMAG" count="1"/>
			<ingredient name="ancientMetalAlloy" count="1"/>
		</recipe>
		<recipe name="armorAncientBoots" count="1" craft_area="legenstation" craft_time="10" tags="learnable,workbenchCrafting,ancientCraft,LCLvl">			
			<ingredient name="ResourceForgedPlatinum" count="1"/>
			<ingredient name="LSAB" count="1"/>
			<ingredient name="LMAB" count="1"/>
			<ingredient name="ancientMetalAlloy" count="1"/>
		</recipe> -->
		<recipe name="meleeAncientmjolnir" count="1" craft_area="legenstation" craft_time="10" tags="learnable,workbenchCrafting,ancientCraft,LCLvl">			
			<ingredient name="legendMelee_GigaHammer" count="1"/>
			<ingredient name="meleeWpnSledgeT3SteelSledgehammerParts" count="1000"/>
			<ingredient name="meleeWpnBatonT2StunBatonParts" count="2000"/>
			<ingredient name="bossTokenAncient" count="1"/>
			<ingredient name="mithril" count="3"/>
		</recipe>		
			
	<!---->
	<!--Nuevos Consumibles-->
		<recipe name="mummyConsuSPE" count="1" craft_area="campfire" craft_time="60" craft_tool="toolCookingPot" tags="perkMasterChef">
			<ingredient name="drinkSPEGrandmaTe" count="2"/>
			<ingredient name="drugSteroids" count="2"/>			
			<ingredient name="drinkJarGrandpasLearningElixir" count="2"/>
			<ingredient name="bossTokenMummy" count="1"/>
			<ingredient name="foodSkillMagazine" count="5"/>
		</recipe>
		<recipe name="juggerConsuSPE" count="1" craft_area="campfire" craft_time="60" craft_tool="toolCookingPot" tags="perkMasterChef,">
			<ingredient name="drugRecog" count="4"/>
			<ingredient name="drugVitamins" count="2"/>			
			<ingredient name="drinkJarBeer" count="10"/>
			<ingredient name="bossTokenJugger" count="1"/>
			<ingredient name="foodSkillMagazine" count="5"/>
		</recipe>
		<recipe name="cirujanoConsuSPE" count="1" craft_area="campfire" craft_time="60" craft_tool="toolCookingPot" tags="perkMasterChef">
			<ingredient name="drugSPEUwuProfen" count="1"/>
			<ingredient name="drugFortBites" count="2"/>			
			<ingredient name="drinkJarPureMineralWater" count="5"/>
			<ingredient name="bossTokenCirujano" count="1"/>
			<ingredient name="foodSkillMagazine" count="5"/>
		</recipe>
		<recipe name="soldierConsuSPE" count="1" craft_area="campfire" craft_time="60" craft_tool="toolCookingPot" tags="perkMasterChef">
			<ingredient name="juguito_de_chale" count="1"/>
			<ingredient name="drugSPEAdrenaline" count="2"/>			
			<ingredient name="drinkJarPureMineralWater" count="1"/>	
			<ingredient name="bossTokenSoldier" count="1"/>
			<ingredient name="foodSkillMagazine" count="5"/>
		</recipe>		

		<recipe name="knightConsuSPE" count="1" craft_area="campfire" craft_time="60" craft_tool="toolCookingPot" tags="perkMasterChef">
			<ingredient name="resourceTestosteroneExtract" count="10"/>			
			<ingredient name="drinkJarGrandpasMoonshine" count="2"/>						
			<ingredient name="bossTokenGadiador" count="1"/>
			<ingredient name="drinkJarBeer" count="10"/>	
			<ingredient name="foodSkillMagazine" count="5"/>		
		</recipe>
	</append>
</configs>